python_tuskarclient-0.1.18.dist-info/WHEEL
python_tuskarclient-0.1.18.dist-info/metadata.json
python_tuskarclient-0.1.18.dist-info/entry_points.txt
python_tuskarclient-0.1.18.dist-info/METADATA
python_tuskarclient-0.1.18.dist-info/RECORD
python_tuskarclient-0.1.18.dist-info/DESCRIPTION.rst
python_tuskarclient-0.1.18.dist-info/pbr.json
python_tuskarclient-0.1.18.dist-info/top_level.txt
tuskarclient/shell.py
tuskarclient/__init__.py
tuskarclient/client.py
tuskarclient/common/auth.py
tuskarclient/common/__init__.py
tuskarclient/common/formatting.py
tuskarclient/common/utils.py
tuskarclient/openstack/__init__.py
tuskarclient/openstack/common/gettextutils.py
tuskarclient/openstack/common/_i18n.py
tuskarclient/openstack/common/__init__.py
tuskarclient/openstack/common/uuidutils.py
tuskarclient/openstack/common/cliutils.py
tuskarclient/openstack/common/apiclient/auth.py
tuskarclient/openstack/common/apiclient/base.py
tuskarclient/openstack/common/apiclient/__init__.py
tuskarclient/openstack/common/apiclient/exceptions.py
tuskarclient/openstack/common/apiclient/client.py
tuskarclient/openstack/common/apiclient/fake_client.py
tuskarclient/openstack/common/apiclient/utils.py
tuskarclient/osc/plugin.py
tuskarclient/osc/__init__.py
tuskarclient/osc/v2/role.py
tuskarclient/osc/v2/__init__.py
tuskarclient/osc/v2/plan.py
tuskarclient/tests/test_client.py
tuskarclient/tests/__init__.py
tuskarclient/tests/test_shell.py
tuskarclient/tests/utils.py
tuskarclient/tests/common/test_formatting.py
tuskarclient/tests/common/test_auth.py
tuskarclient/tests/common/test_utils.py
tuskarclient/tests/common/__init__.py
tuskarclient/tests/osc/__init__.py
tuskarclient/tests/osc/test_plugin.py
tuskarclient/tests/osc/v2/fakes.py
tuskarclient/tests/osc/v2/__init__.py
tuskarclient/tests/osc/v2/test_roles.py
tuskarclient/tests/osc/v2/test_plans.py
tuskarclient/tests/integration/test_help_command.py
tuskarclient/tests/integration/__init__.py
tuskarclient/tests/v2/test_roles_shell.py
tuskarclient/tests/v2/test_client.py
tuskarclient/tests/v2/__init__.py
tuskarclient/tests/v2/test_roles.py
tuskarclient/tests/v2/test_plans.py
tuskarclient/tests/v2/test_plans_shell.py
tuskarclient/v2/roles.py
tuskarclient/v2/shell.py
tuskarclient/v2/__init__.py
tuskarclient/v2/plans.py
tuskarclient/v2/roles_shell.py
tuskarclient/v2/client.py
