Metadata-Version: 2.0
Name: python-tuskarclient
Version: 0.1.18
Summary: Client library for OpenStack Management API
Home-page: https://github.com/openstack/python-tuskarclient
Author: Jiri Stransky
Author-email: jistr@redhat.com
License: Apache License, Version 2.0
Platform: UNKNOWN
Classifier: Environment :: Console
Classifier: Environment :: OpenStack
Classifier: Intended Audience :: Developers
Classifier: Intended Audience :: Information Technology
Classifier: License :: OSI Approved :: Apache Software License
Classifier: Operating System :: OS Independent
Classifier: Programming Language :: Python
Classifier: Programming Language :: Python :: 2
Classifier: Programming Language :: Python :: 2.7
Classifier: Programming Language :: Python :: 3
Classifier: Programming Language :: Python :: 3.3
Requires-Dist: pbr (>=0.6,!=0.7,<1.0)
Requires-Dist: Babel (>=1.3)
Requires-Dist: cliff (>=1.10.0)
Requires-Dist: iso8601 (>=0.1.9)
Requires-Dist: PrettyTable (>=0.7,<0.8)
Requires-Dist: python-keystoneclient (>=1.3.0)
Requires-Dist: requests (>=2.5.2)
Requires-Dist: python-openstackclient (>=1.0.0)
Requires-Dist: simplejson (>=2.2.0)
Requires-Dist: six (>=1.9.0)
